ui_components/__init__.py
ui_components/compiler.py
ui_components/components.py
ui_components/js/add_multiselect_option.js
ui_components/js/chart.js
ui_components/js/clear_multiselect_options.js
ui_components/js/clear_select_options.js
ui_components/js/get_data.js
ui_components/js/get_multiselect_options.js
ui_components/js/get_select_options.js
ui_components/js/ioinfo.js
ui_components/js/set_select_options.js
ui_components/js/set_vega_grid.js
ui_components/js/table.js
ui_components/js/tabs.js
ui_components/js/title_case.js
ui_components/styles/flex.css
ui_components/styles/kvt.css
ui_components/styles/pagination.css
ui_components/styles/search.css
ui_components/styles/side_nav.css
ui_components/styles/table.css
ui_components/styles/top_nav.css
ui_components/styles.py
ui_components/utils.py
ui_components-0.2.8.dist-info/WHEEL
ui_components-0.2.8.dist-info/METADATA
ui_components-0.2.8.dist-info/RECORD
