Metadata-Version: 2.1
Name: ui-components
Version: 0.2.8
Summary: 
Author: Dan
Author-email: kelleherjdan@gmail.com
Requires-Python: >=3.9,<4.0
Classifier: Programming Language :: Python :: 3
Classifier: Programming Language :: Python :: 3.10
Classifier: Programming Language :: Python :: 3.9
Requires-Dist: cssselect (>=1.1.0,<2.0.0)
Requires-Dist: dominate (>=2.6.0,<3.0.0)
Requires-Dist: lxml (>=4.9.0,<5.0.0)
Requires-Dist: pydantic (>=1.9.1,<2.0.0)
Requires-Dist: ready-logger (>=0.1.4,<0.2.0)
